lowflows/__init__.py
lowflows/core.py
lowflows/read_data.py
lowflows/reporting.py
lowflows/util.py
lowflows/tests/__init__.py
lowflows/tests/test_lowflows.py
lowflows-0.1.2.dist-info/LICENSE.txt
lowflows-0.1.2.dist-info/METADATA
lowflows-0.1.2.dist-info/WHEEL
lowflows-0.1.2.dist-info/top_level.txt
lowflows-0.1.2.dist-info/RECORD
