Metadata-Version: 2.1
Name: lowflows
Version: 0.1.2
Summary: Functions to query ECan lowflows
Home-page: https://github.com/Data-to-Knowledge/lowflows
Author: Mike Kittridge
Author-email: mullenkamp1@gmail.com
License: Apache
Keywords: ecan lowflows
Platform: UNKNOWN
Classifier: Development Status :: 3 - Alpha
Classifier: Intended Audience :: Developers
Classifier: Topic :: Software Development :: Build Tools
Classifier: License :: OSI Approved :: Apache Software License
Classifier: Programming Language :: Python :: 2
Classifier: Programming Language :: Python :: 2.7
Classifier: Programming Language :: Python :: 3
Classifier: Programming Language :: Python :: 3.4
Classifier: Programming Language :: Python :: 3.5
Classifier: Programming Language :: Python :: 3.6
Requires-Dist: pandas
Requires-Dist: pdsql
